bilingual_bot/__init__.py
bilingual_bot/main.py
Bilingual_conversational_bot-0.1.dist-info/METADATA
Bilingual_conversational_bot-0.1.dist-info/WHEEL
Bilingual_conversational_bot-0.1.dist-info/entry_points.txt
Bilingual_conversational_bot-0.1.dist-info/top_level.txt
Bilingual_conversational_bot-0.1.dist-info/RECORD
