Metadata-Version: 2.1
Name: Bilingual-conversational-bot
Version: 0.1
Summary: A Real-Time Live Bilingual Conversation bot for English to Spanish and Spanish to English using Streamlit
Author: Palash Dandge
Classifier: Programming Language :: Python :: 3
Classifier: License :: OSI Approved :: MIT License
Classifier: Operating System :: OS Independent
Requires-Dist: streamlit
Requires-Dist: googletrans ==4.0.0-rc1
Requires-Dist: SpeechRecognition
Requires-Dist: gtts
Requires-Dist: pydub
Requires-Dist: pyaudio
